kataflash/__init__.py
kataflash/__main__.py
kataflash/upstream/__init__.py
kataflash/upstream/flashtool.py
kataflash/upstream/info.py
kataflash-0.0.1.dev1.dist-info/METADATA
kataflash-0.0.1.dev1.dist-info/WHEEL
kataflash-0.0.1.dev1.dist-info/entry_points.txt
kataflash-0.0.1.dev1.dist-info/top_level.txt
kataflash-0.0.1.dev1.dist-info/RECORD
