Metadata-Version: 2.4
Name: kataflash
Version: 0.0.1.dev1
Requires-Python: >=3.7
Requires-Dist: pyserial
